<annotation>
	<folder>JPEGImages</folder>
	<filename>good31.png</filename>
	<path>D:\Project\data\VOCdevkit\VOC2007\JPEGImages\good31.png</path>
	<source>
		<database>Unknown</database>
	</source>
	<size>
		<width>1639</width>
		<height>569</height>
		<depth>3</depth>
	</size>
	<segmented>0</segmented>
	<object>
		<name>good</name>
		<pose>Unspecified</pose>
		<truncated>0</truncated>
		<difficult>0</difficult>
		<bndbox>
			<xmin>32</xmin>
			<ymin>54</ymin>
			<xmax>116</xmax>
			<ymax>149</ymax>
		</bndbox>
	</object>
	<object>
		<name>good</name>
		<pose>Unspecified</pose>
		<truncated>0</truncated>
		<difficult>0</difficult>
		<bndbox>
			<xmin>33</xmin>
			<ymin>231</ymin>
			<xmax>129</xmax>
			<ymax>330</ymax>
		</bndbox>
	</object>
	<object>
		<name>good</name>
		<pose>Unspecified</pose>
		<truncated>0</truncated>
		<difficult>0</difficult>
		<bndbox>
			<xmin>34</xmin>
			<ymin>396</ymin>
			<xmax>138</xmax>
			<ymax>510</ymax>
		</bndbox>
	</object>
	<object>
		<name>good</name>
		<pose>Unspecified</pose>
		<truncated>0</truncated>
		<difficult>0</difficult>
		<bndbox>
			<xmin>193</xmin>
			<ymin>399</ymin>
			<xmax>299</xmax>
			<ymax>511</ymax>
		</bndbox>
	</object>
	<object>
		<name>good</name>
		<pose>Unspecified</pose>
		<truncated>0</truncated>
		<difficult>0</difficult>
		<bndbox>
			<xmin>200</xmin>
			<ymin>227</ymin>
			<xmax>290</xmax>
			<ymax>337</ymax>
		</bndbox>
	</object>
	<object>
		<name>good</name>
		<pose>Unspecified</pose>
		<truncated>0</truncated>
		<difficult>0</difficult>
		<bndbox>
			<xmin>203</xmin>
			<ymin>42</ymin>
			<xmax>298</xmax>
			<ymax>145</ymax>
		</bndbox>
	</object>
	<object>
		<name>good</name>
		<pose>Unspecified</pose>
		<truncated>0</truncated>
		<difficult>0</difficult>
		<bndbox>
			<xmin>361</xmin>
			<ymin>51</ymin>
			<xmax>461</xmax>
			<ymax>146</ymax>
		</bndbox>
	</object>
	<object>
		<name>good</name>
		<pose>Unspecified</pose>
		<truncated>0</truncated>
		<difficult>0</difficult>
		<bndbox>
			<xmin>361</xmin>
			<ymin>224</ymin>
			<xmax>445</xmax>
			<ymax>330</ymax>
		</bndbox>
	</object>
	<object>
		<name>good</name>
		<pose>Unspecified</pose>
		<truncated>0</truncated>
		<difficult>0</difficult>
		<bndbox>
			<xmin>364</xmin>
			<ymin>400</ymin>
			<xmax>465</xmax>
			<ymax>509</ymax>
		</bndbox>
	</object>
	<object>
		<name>good</name>
		<pose>Unspecified</pose>
		<truncated>0</truncated>
		<difficult>0</difficult>
		<bndbox>
			<xmin>506</xmin>
			<ymin>407</ymin>
			<xmax>608</xmax>
			<ymax>517</ymax>
		</bndbox>
	</object>
	<object>
		<name>good</name>
		<pose>Unspecified</pose>
		<truncated>0</truncated>
		<difficult>0</difficult>
		<bndbox>
			<xmin>678</xmin>
			<ymin>404</ymin>
			<xmax>772</xmax>
			<ymax>512</ymax>
		</bndbox>
	</object>
	<object>
		<name>good</name>
		<pose>Unspecified</pose>
		<truncated>0</truncated>
		<difficult>0</difficult>
		<bndbox>
			<xmin>844</xmin>
			<ymin>405</ymin>
			<xmax>936</xmax>
			<ymax>500</ymax>
		</bndbox>
	</object>
	<object>
		<name>good</name>
		<pose>Unspecified</pose>
		<truncated>0</truncated>
		<difficult>0</difficult>
		<bndbox>
			<xmin>998</xmin>
			<ymin>403</ymin>
			<xmax>1095</xmax>
			<ymax>507</ymax>
		</bndbox>
	</object>
	<object>
		<name>good</name>
		<pose>Unspecified</pose>
		<truncated>0</truncated>
		<difficult>0</difficult>
		<bndbox>
			<xmin>1163</xmin>
			<ymin>404</ymin>
			<xmax>1264</xmax>
			<ymax>507</ymax>
		</bndbox>
	</object>
	<object>
		<name>good</name>
		<pose>Unspecified</pose>
		<truncated>0</truncated>
		<difficult>0</difficult>
		<bndbox>
			<xmin>1329</xmin>
			<ymin>408</ymin>
			<xmax>1429</xmax>
			<ymax>505</ymax>
		</bndbox>
	</object>
	<object>
		<name>good</name>
		<pose>Unspecified</pose>
		<truncated>0</truncated>
		<difficult>0</difficult>
		<bndbox>
			<xmin>1487</xmin>
			<ymin>411</ymin>
			<xmax>1582</xmax>
			<ymax>504</ymax>
		</bndbox>
	</object>
	<object>
		<name>good</name>
		<pose>Unspecified</pose>
		<truncated>0</truncated>
		<difficult>0</difficult>
		<bndbox>
			<xmin>1492</xmin>
			<ymin>234</ymin>
			<xmax>1585</xmax>
			<ymax>326</ymax>
		</bndbox>
	</object>
	<object>
		<name>good</name>
		<pose>Unspecified</pose>
		<truncated>0</truncated>
		<difficult>0</difficult>
		<bndbox>
			<xmin>1328</xmin>
			<ymin>225</ymin>
			<xmax>1443</xmax>
			<ymax>344</ymax>
		</bndbox>
	</object>
	<object>
		<name>good</name>
		<pose>Unspecified</pose>
		<truncated>0</truncated>
		<difficult>0</difficult>
		<bndbox>
			<xmin>1164</xmin>
			<ymin>226</ymin>
			<xmax>1252</xmax>
			<ymax>327</ymax>
		</bndbox>
	</object>
	<object>
		<name>good</name>
		<pose>Unspecified</pose>
		<truncated>0</truncated>
		<difficult>0</difficult>
		<bndbox>
			<xmin>999</xmin>
			<ymin>227</ymin>
			<xmax>1101</xmax>
			<ymax>325</ymax>
		</bndbox>
	</object>
	<object>
		<name>good</name>
		<pose>Unspecified</pose>
		<truncated>0</truncated>
		<difficult>0</difficult>
		<bndbox>
			<xmin>835</xmin>
			<ymin>231</ymin>
			<xmax>935</xmax>
			<ymax>337</ymax>
		</bndbox>
	</object>
	<object>
		<name>good</name>
		<pose>Unspecified</pose>
		<truncated>0</truncated>
		<difficult>0</difficult>
		<bndbox>
			<xmin>677</xmin>
			<ymin>230</ymin>
			<xmax>782</xmax>
			<ymax>325</ymax>
		</bndbox>
	</object>
	<object>
		<name>good</name>
		<pose>Unspecified</pose>
		<truncated>0</truncated>
		<difficult>0</difficult>
		<bndbox>
			<xmin>523</xmin>
			<ymin>231</ymin>
			<xmax>613</xmax>
			<ymax>326</ymax>
		</bndbox>
	</object>
	<object>
		<name>good</name>
		<pose>Unspecified</pose>
		<truncated>0</truncated>
		<difficult>0</difficult>
		<bndbox>
			<xmin>525</xmin>
			<ymin>48</ymin>
			<xmax>616</xmax>
			<ymax>144</ymax>
		</bndbox>
	</object>
	<object>
		<name>good</name>
		<pose>Unspecified</pose>
		<truncated>0</truncated>
		<difficult>0</difficult>
		<bndbox>
			<xmin>687</xmin>
			<ymin>36</ymin>
			<xmax>785</xmax>
			<ymax>152</ymax>
		</bndbox>
	</object>
	<object>
		<name>good</name>
		<pose>Unspecified</pose>
		<truncated>0</truncated>
		<difficult>0</difficult>
		<bndbox>
			<xmin>855</xmin>
			<ymin>51</ymin>
			<xmax>931</xmax>
			<ymax>136</ymax>
		</bndbox>
	</object>
	<object>
		<name>good</name>
		<pose>Unspecified</pose>
		<truncated>0</truncated>
		<difficult>0</difficult>
		<bndbox>
			<xmin>987</xmin>
			<ymin>46</ymin>
			<xmax>1098</xmax>
			<ymax>167</ymax>
		</bndbox>
	</object>
	<object>
		<name>good</name>
		<pose>Unspecified</pose>
		<truncated>0</truncated>
		<difficult>0</difficult>
		<bndbox>
			<xmin>1172</xmin>
			<ymin>56</ymin>
			<xmax>1269</xmax>
			<ymax>164</ymax>
		</bndbox>
	</object>
	<object>
		<name>good</name>
		<pose>Unspecified</pose>
		<truncated>0</truncated>
		<difficult>0</difficult>
		<bndbox>
			<xmin>1305</xmin>
			<ymin>42</ymin>
			<xmax>1429</xmax>
			<ymax>152</ymax>
		</bndbox>
	</object>
	<object>
		<name>good</name>
		<pose>Unspecified</pose>
		<truncated>0</truncated>
		<difficult>0</difficult>
		<bndbox>
			<xmin>1498</xmin>
			<ymin>44</ymin>
			<xmax>1572</xmax>
			<ymax>150</ymax>
		</bndbox>
	</object>
</annotation>
